<?xml version="1.0" encoding="UTF-8"?>
<report-definition xmlns="http://jfreereport.sourceforge.net/namespaces/reports/legacy/ext" name="Report" engine-version="0.8.9.8">
  <parser-config>
    <object-factory class="org.jfree.report.modules.parser.ext.factory.base.URLClassFactory"/>
    <object-factory class="org.jfree.report.modules.parser.ext.factory.objects.DefaultClassFactory"/>
    <object-factory class="org.jfree.report.modules.parser.ext.factory.objects.BandLayoutClassFactory"/>
    <object-factory class="org.jfree.report.modules.parser.ext.factory.base.ArrayClassFactory"/>
    <element-factory class="org.jfree.report.modules.parser.ext.factory.elements.DefaultElementFactory"/>
    <stylekey-factory class="org.jfree.report.modules.parser.ext.factory.stylekey.DefaultStyleKeyFactory"/>
    <stylekey-factory class="org.jfree.report.modules.parser.ext.factory.stylekey.PageableLayoutStyleKeyFactory"/>
    <template-factory class="org.jfree.report.modules.parser.ext.factory.templates.DefaultTemplateCollection"/>
    <datasource-factory class="org.jfree.report.modules.parser.ext.factory.datasource.DefaultDataSourceFactory"/>
  </parser-config>
  <report-config>
    <simple-page-definition width="1" height="1">
      <page orientation="portrait" topmargin="56" leftmargin="85" bottommargin="56" rightmargin="28" pageformat="A4"/>
    </simple-page-definition>
    <configuration>
      <property name="org.jfree.report.NoPrinterAvailable">true</property>
    </configuration>
  </report-config>
  <report-description>
    <report-header>
      <style>
        <basic-key name="pagebreak-before">false</basic-key>
        <basic-key name="pagebreak-after">false</basic-key>
        <basic-key name="border-top-width">1.0</basic-key>
        <basic-key name="border-top-style">none</basic-key>
        <basic-key name="border-top-color">black</basic-key>
        <basic-key name="border-left-width">1.0</basic-key>
        <basic-key name="border-left-style">none</basic-key>
        <basic-key name="border-left-color">black</basic-key>
        <basic-key name="border-bottom-width">1.0</basic-key>
        <basic-key name="border-bottom-style">none</basic-key>
        <basic-key name="border-bottom-color">black</basic-key>
        <basic-key name="border-right-width">1.0</basic-key>
        <basic-key name="border-right-style">none</basic-key>
        <basic-key name="border-right-color">black</basic-key>
        <basic-key name="border-break-width">0.0</basic-key>
        <basic-key name="border-break-style">none</basic-key>
        <basic-key name="border-break-color">black</basic-key>
        <basic-key name="border-top-right-radius-width">0.0</basic-key>
        <basic-key name="border-top-left-radius-width">0.0</basic-key>
        <basic-key name="border-bottom-right-radius-width">0.0</basic-key>
        <basic-key name="border-bottom-left-radius-width">0.0</basic-key>
        <basic-key name="border-top-right-radius-height">0.0</basic-key>
        <basic-key name="border-top-left-radius-height">0.0</basic-key>
        <basic-key name="border-bottom-right-radius-height">0.0</basic-key>
        <basic-key name="border-bottom-left-radius-height">0.0</basic-key>
        <basic-key name="padding-left">0.0</basic-key>
        <basic-key name="padding-top">0.0</basic-key>
        <basic-key name="padding-bottom">0.0</basic-key>
        <basic-key name="padding-right">0.0</basic-key>
      </style>
      <element name="Element@1836774267" type="text/plain">
        <style>
          <basic-key name="border-top-width">1.0</basic-key>
          <basic-key name="border-top-style">none</basic-key>
          <basic-key name="border-top-color">black</basic-key>
          <basic-key name="border-left-width">1.0</basic-key>
          <basic-key name="border-left-style">none</basic-key>
          <basic-key name="border-left-color">black</basic-key>
          <basic-key name="border-bottom-width">1.0</basic-key>
          <basic-key name="border-bottom-style">none</basic-key>
          <basic-key name="border-bottom-color">black</basic-key>
          <basic-key name="border-right-width">1.0</basic-key>
          <basic-key name="border-right-style">none</basic-key>
          <basic-key name="border-right-color">black</basic-key>
          <basic-key name="border-break-width">0.0</basic-key>
          <basic-key name="border-break-style">none</basic-key>
          <basic-key name="border-break-color">black</basic-key>
          <basic-key name="border-top-right-radius-width">0.0</basic-key>
          <basic-key name="border-top-left-radius-width">0.0</basic-key>
          <basic-key name="border-bottom-right-radius-width">0.0</basic-key>
          <basic-key name="border-bottom-left-radius-width">0.0</basic-key>
          <basic-key name="border-top-right-radius-height">0.0</basic-key>
          <basic-key name="border-top-left-radius-height">0.0</basic-key>
          <basic-key name="border-bottom-right-radius-height">0.0</basic-key>
          <basic-key name="border-bottom-left-radius-height">0.0</basic-key>
          <basic-key name="padding-left">0.0</basic-key>
          <basic-key name="padding-top">0.0</basic-key>
          <basic-key name="padding-bottom">0.0</basic-key>
          <basic-key name="padding-right">0.0</basic-key>
          <basic-key name="x">4.3423424</basic-key>
          <basic-key name="y">100.0</basic-key>
          <basic-key name="min-width">178.03604</basic-key>
          <basic-key name="min-height">25.0</basic-key>
          <basic-key name="paint">black</basic-key>
          <basic-key name="alignment">center</basic-key>
          <basic-key name="valignment">middle</basic-key>
          <basic-key name="dynamic_height">false</basic-key>
          <basic-key name="Excel.WrapText">true</basic-key>
          <basic-key name="font">Arial Unicode MS</basic-key>
          <basic-key name="font-size">12</basic-key>
          <basic-key name="line-height">0.0</basic-key>
          <basic-key name="font-bold">false</basic-key>
          <basic-key name="font-italic">false</basic-key>
          <basic-key name="font-underline">false</basic-key>
          <basic-key name="font-strikethrough">false</basic-key>
          <basic-key name="font-embedded">true</basic-key>
          <basic-key name="font-encoding">UTF-8</basic-key>
          <basic-key name="reserved-literal">..</basic-key>
          <basic-key name="trim-text-content">false</basic-key>
        </style>
        <template references="message-field">
          <basic-object name="format">«$(CURRENT_DATE_DAY)» $(CURRENT_DATE_MONTH) $(CURRENT_DATE_YEAR)г.</basic-object>
          <basic-object name="nullValue"></basic-object>
        </template>
      </element>
      <element name="Element@518287145" type="text/plain">
        <style>
          <basic-key name="border-top-width">1.0</basic-key>
          <basic-key name="border-top-style">none</basic-key>
          <basic-key name="border-top-color">black</basic-key>
          <basic-key name="border-left-width">1.0</basic-key>
          <basic-key name="border-left-style">none</basic-key>
          <basic-key name="border-left-color">black</basic-key>
          <basic-key name="border-bottom-width">1.0</basic-key>
          <basic-key name="border-bottom-style">none</basic-key>
          <basic-key name="border-bottom-color">black</basic-key>
          <basic-key name="border-right-width">1.0</basic-key>
          <basic-key name="border-right-style">none</basic-key>
          <basic-key name="border-right-color">black</basic-key>
          <basic-key name="border-break-width">0.0</basic-key>
          <basic-key name="border-break-style">none</basic-key>
          <basic-key name="border-break-color">black</basic-key>
          <basic-key name="border-top-right-radius-width">0.0</basic-key>
          <basic-key name="border-top-left-radius-width">0.0</basic-key>
          <basic-key name="border-bottom-right-radius-width">0.0</basic-key>
          <basic-key name="border-bottom-left-radius-width">0.0</basic-key>
          <basic-key name="border-top-right-radius-height">0.0</basic-key>
          <basic-key name="border-top-left-radius-height">0.0</basic-key>
          <basic-key name="border-bottom-right-radius-height">0.0</basic-key>
          <basic-key name="border-bottom-left-radius-height">0.0</basic-key>
          <basic-key name="padding-left">0.0</basic-key>
          <basic-key name="padding-top">0.0</basic-key>
          <basic-key name="padding-bottom">0.0</basic-key>
          <basic-key name="padding-right">0.0</basic-key>
          <basic-key name="x">373.44144</basic-key>
          <basic-key name="y">100.0</basic-key>
          <basic-key name="min-width">104.21622</basic-key>
          <basic-key name="min-height">25.0</basic-key>
          <basic-key name="paint">black</basic-key>
          <basic-key name="alignment">left</basic-key>
          <basic-key name="valignment">middle</basic-key>
          <basic-key name="dynamic_height">false</basic-key>
          <basic-key name="Excel.WrapText">true</basic-key>
          <basic-key name="font">Arial Unicode MS</basic-key>
          <basic-key name="font-size">12</basic-key>
          <basic-key name="line-height">0.0</basic-key>
          <basic-key name="font-bold">false</basic-key>
          <basic-key name="font-italic">false</basic-key>
          <basic-key name="font-underline">false</basic-key>
          <basic-key name="font-strikethrough">false</basic-key>
          <basic-key name="font-embedded">true</basic-key>
          <basic-key name="font-encoding">UTF-8</basic-key>
          <basic-key name="reserved-literal">..</basic-key>
          <basic-key name="trim-text-content">false</basic-key>
        </style>
        <template references="message-field">
          <basic-object name="format">№ $(PRIKAZ_NUMBER)</basic-object>
          <basic-object name="nullValue"></basic-object>
        </template>
      </element>
      <element name="Element@1170309821" type="text/plain">
        <style>
          <basic-key name="border-top-width">1.0</basic-key>
          <basic-key name="border-top-style">none</basic-key>
          <basic-key name="border-top-color">black</basic-key>
          <basic-key name="border-left-width">1.0</basic-key>
          <basic-key name="border-left-style">none</basic-key>
          <basic-key name="border-left-color">black</basic-key>
          <basic-key name="border-bottom-width">1.0</basic-key>
          <basic-key name="border-bottom-style">none</basic-key>
          <basic-key name="border-bottom-color">black</basic-key>
          <basic-key name="border-right-width">1.0</basic-key>
          <basic-key name="border-right-style">none</basic-key>
          <basic-key name="border-right-color">black</basic-key>
          <basic-key name="border-break-width">0.0</basic-key>
          <basic-key name="border-break-style">none</basic-key>
          <basic-key name="border-break-color">black</basic-key>
          <basic-key name="border-top-right-radius-width">0.0</basic-key>
          <basic-key name="border-top-left-radius-width">0.0</basic-key>
          <basic-key name="border-bottom-right-radius-width">0.0</basic-key>
          <basic-key name="border-bottom-left-radius-width">0.0</basic-key>
          <basic-key name="border-top-right-radius-height">0.0</basic-key>
          <basic-key name="border-top-left-radius-height">0.0</basic-key>
          <basic-key name="border-bottom-right-radius-height">0.0</basic-key>
          <basic-key name="border-bottom-left-radius-height">0.0</basic-key>
          <basic-key name="padding-left">0.0</basic-key>
          <basic-key name="padding-top">0.0</basic-key>
          <basic-key name="padding-bottom">0.0</basic-key>
          <basic-key name="padding-right">0.0</basic-key>
          <basic-key name="x">65.13513</basic-key>
          <basic-key name="y">125.0</basic-key>
          <basic-key name="min-width">43.423424</basic-key>
          <basic-key name="min-height">22.0</basic-key>
          <basic-key name="paint">black</basic-key>
          <basic-key name="alignment">center</basic-key>
          <basic-key name="valignment">top</basic-key>
          <basic-key name="dynamic_height">false</basic-key>
          <basic-key name="Excel.WrapText">true</basic-key>
          <basic-key name="font">Arial Unicode MS</basic-key>
          <basic-key name="font-size">12</basic-key>
          <basic-key name="line-height">0.0</basic-key>
          <basic-key name="font-bold">false</basic-key>
          <basic-key name="font-italic">false</basic-key>
          <basic-key name="font-underline">false</basic-key>
          <basic-key name="font-strikethrough">false</basic-key>
          <basic-key name="font-embedded">true</basic-key>
          <basic-key name="font-encoding">UTF-8</basic-key>
          <basic-key name="reserved-literal">..</basic-key>
          <basic-key name="trim-text-content">false</basic-key>
        </style>
        <template references="label">
          <basic-object name="content">г. Орел</basic-object>
        </template>
      </element>
      <element name="Element@1630428335" type="text/plain">
        <style>
          <basic-key name="border-top-width">1.0</basic-key>
          <basic-key name="border-top-style">none</basic-key>
          <basic-key name="border-top-color">black</basic-key>
          <basic-key name="border-left-width">1.0</basic-key>
          <basic-key name="border-left-style">none</basic-key>
          <basic-key name="border-left-color">black</basic-key>
          <basic-key name="border-bottom-width">1.0</basic-key>
          <basic-key name="border-bottom-style">none</basic-key>
          <basic-key name="border-bottom-color">black</basic-key>
          <basic-key name="border-right-width">1.0</basic-key>
          <basic-key name="border-right-style">none</basic-key>
          <basic-key name="border-right-color">black</basic-key>
          <basic-key name="border-break-width">0.0</basic-key>
          <basic-key name="border-break-style">none</basic-key>
          <basic-key name="border-break-color">black</basic-key>
          <basic-key name="border-top-right-radius-width">0.0</basic-key>
          <basic-key name="border-top-left-radius-width">0.0</basic-key>
          <basic-key name="border-bottom-right-radius-width">0.0</basic-key>
          <basic-key name="border-bottom-left-radius-width">0.0</basic-key>
          <basic-key name="border-top-right-radius-height">0.0</basic-key>
          <basic-key name="border-top-left-radius-height">0.0</basic-key>
          <basic-key name="border-bottom-right-radius-height">0.0</basic-key>
          <basic-key name="border-bottom-left-radius-height">0.0</basic-key>
          <basic-key name="padding-left">0.0</basic-key>
          <basic-key name="padding-top">0.0</basic-key>
          <basic-key name="padding-bottom">0.0</basic-key>
          <basic-key name="padding-right">0.0</basic-key>
          <basic-key name="x">4.3423424</basic-key>
          <basic-key name="y">170.0</basic-key>
          <basic-key name="min-width">325.6757</basic-key>
          <basic-key name="min-height">50.0</basic-key>
          <basic-key name="paint">black</basic-key>
          <basic-key name="alignment">left</basic-key>
          <basic-key name="valignment">top</basic-key>
          <basic-key name="dynamic_height">true</basic-key>
          <basic-key name="Excel.WrapText">true</basic-key>
          <basic-key name="font">Arial Unicode MS</basic-key>
          <basic-key name="font-size">12</basic-key>
          <basic-key name="line-height">0.0</basic-key>
          <basic-key name="font-bold">false</basic-key>
          <basic-key name="font-italic">false</basic-key>
          <basic-key name="font-underline">false</basic-key>
          <basic-key name="font-strikethrough">false</basic-key>
          <basic-key name="font-embedded">true</basic-key>
          <basic-key name="font-encoding">UTF-8</basic-key>
          <basic-key name="reserved-literal">..</basic-key>
          <basic-key name="trim-text-content">false</basic-key>
        </style>
        <template references="message-field">
          <basic-object name="format">Об отказе в возобновлении действия лицензии № $(LICENSE_NUMBER)
на розничную продажу алкогольной продукции
$(AGENT_NAME)</basic-object>
          <basic-object name="nullValue"></basic-object>
        </template>
      </element>
      <element name="Element@540523637" type="text/plain">
        <style>
          <basic-key name="border-top-width">1.0</basic-key>
          <basic-key name="border-top-style">none</basic-key>
          <basic-key name="border-top-color">black</basic-key>
          <basic-key name="border-left-width">1.0</basic-key>
          <basic-key name="border-left-style">none</basic-key>
          <basic-key name="border-left-color">black</basic-key>
          <basic-key name="border-bottom-width">1.0</basic-key>
          <basic-key name="border-bottom-style">none</basic-key>
          <basic-key name="border-bottom-color">black</basic-key>
          <basic-key name="border-right-width">1.0</basic-key>
          <basic-key name="border-right-style">none</basic-key>
          <basic-key name="border-right-color">black</basic-key>
          <basic-key name="border-break-width">0.0</basic-key>
          <basic-key name="border-break-style">none</basic-key>
          <basic-key name="border-break-color">black</basic-key>
          <basic-key name="border-top-right-radius-width">0.0</basic-key>
          <basic-key name="border-top-left-radius-width">0.0</basic-key>
          <basic-key name="border-bottom-right-radius-width">0.0</basic-key>
          <basic-key name="border-bottom-left-radius-width">0.0</basic-key>
          <basic-key name="border-top-right-radius-height">0.0</basic-key>
          <basic-key name="border-top-left-radius-height">0.0</basic-key>
          <basic-key name="border-bottom-right-radius-height">0.0</basic-key>
          <basic-key name="border-bottom-left-radius-height">0.0</basic-key>
          <basic-key name="padding-left">0.0</basic-key>
          <basic-key name="padding-top">0.0</basic-key>
          <basic-key name="padding-bottom">0.0</basic-key>
          <basic-key name="padding-right">0.0</basic-key>
          <basic-key name="x">4.3423424</basic-key>
          <basic-key name="y">260.0</basic-key>
          <basic-key name="min-width">477.65765</basic-key>
          <basic-key name="min-height">120.0</basic-key>
          <basic-key name="paint">black</basic-key>
          <basic-key name="alignment">left</basic-key>
          <basic-key name="valignment">top</basic-key>
          <basic-key name="dynamic_height">true</basic-key>
          <basic-key name="Excel.WrapText">true</basic-key>
          <basic-key name="font">Arial Unicode MS</basic-key>
          <basic-key name="font-size">12</basic-key>
          <basic-key name="line-height">0.0</basic-key>
          <basic-key name="font-bold">false</basic-key>
          <basic-key name="font-italic">false</basic-key>
          <basic-key name="font-underline">false</basic-key>
          <basic-key name="font-strikethrough">false</basic-key>
          <basic-key name="font-embedded">true</basic-key>
          <basic-key name="font-encoding">UTF-8</basic-key>
          <basic-key name="reserved-literal">..</basic-key>
          <basic-key name="trim-text-content">false</basic-key>
        </style>
        <template references="message-field">
          <basic-object name="format">В соответствии с Федеральным законом от 22.11.1995г. №171-ФЗ «О государственном регулировании производства и оборота этилового спирта, алкогольной и спиртосодержащей продукции» (в ред. Федерального закона от 21.07.2005 г. №102-ФЗ), законом Орловской области от 26.12.2005г. №564-ОЗ «О государственном регулировании производства и оборота этилового спирта алкогольной и спиртосодержащей продукции на территории Орловской области», на основании акта внеплановой проверки от $(CTRL_ACT_DATE)г. № $(CTRL_ACT_NUM) по информации лицензиата от $(field16)г. об устранении нарушений условий и требований на розничную продажу алкогольной продукции, послуживших основанием для приостановления действия лицензии П Р И К А З Ы В А Ю:
   </basic-object>
          <basic-object name="nullValue"></basic-object>
        </template>
      </element>
      <element name="Element@531225309" type="text/plain">
        <style>
          <basic-key name="border-top-width">1.0</basic-key>
          <basic-key name="border-top-style">none</basic-key>
          <basic-key name="border-top-color">black</basic-key>
          <basic-key name="border-left-width">1.0</basic-key>
          <basic-key name="border-left-style">none</basic-key>
          <basic-key name="border-left-color">black</basic-key>
          <basic-key name="border-bottom-width">1.0</basic-key>
          <basic-key name="border-bottom-style">none</basic-key>
          <basic-key name="border-bottom-color">black</basic-key>
          <basic-key name="border-right-width">1.0</basic-key>
          <basic-key name="border-right-style">none</basic-key>
          <basic-key name="border-right-color">black</basic-key>
          <basic-key name="border-break-width">0.0</basic-key>
          <basic-key name="border-break-style">none</basic-key>
          <basic-key name="border-break-color">black</basic-key>
          <basic-key name="border-top-right-radius-width">0.0</basic-key>
          <basic-key name="border-top-left-radius-width">0.0</basic-key>
          <basic-key name="border-bottom-right-radius-width">0.0</basic-key>
          <basic-key name="border-bottom-left-radius-width">0.0</basic-key>
          <basic-key name="border-top-right-radius-height">0.0</basic-key>
          <basic-key name="border-top-left-radius-height">0.0</basic-key>
          <basic-key name="border-bottom-right-radius-height">0.0</basic-key>
          <basic-key name="border-bottom-left-radius-height">0.0</basic-key>
          <basic-key name="padding-left">0.0</basic-key>
          <basic-key name="padding-top">0.0</basic-key>
          <basic-key name="padding-bottom">0.0</basic-key>
          <basic-key name="padding-right">0.0</basic-key>
          <basic-key name="x">0.0</basic-key>
          <basic-key name="y">0.0</basic-key>
          <basic-key name="min-width">482.0</basic-key>
          <basic-key name="min-height">20.0</basic-key>
          <basic-key name="paint">black</basic-key>
          <basic-key name="alignment">center</basic-key>
          <basic-key name="valignment">middle</basic-key>
          <basic-key name="dynamic_height">false</basic-key>
          <basic-key name="Excel.WrapText">true</basic-key>
          <basic-key name="font">Arial Unicode MS</basic-key>
          <basic-key name="font-size">14</basic-key>
          <basic-key name="line-height">0.0</basic-key>
          <basic-key name="font-bold">false</basic-key>
          <basic-key name="font-italic">false</basic-key>
          <basic-key name="font-underline">false</basic-key>
          <basic-key name="font-strikethrough">false</basic-key>
          <basic-key name="font-embedded">true</basic-key>
          <basic-key name="font-encoding">UTF-8</basic-key>
          <basic-key name="reserved-literal">..</basic-key>
          <basic-key name="trim-text-content">false</basic-key>
        </style>
        <template references="label">
          <basic-object name="content">РОССИЙСКАЯ ФЕДЕРАЦИЯ</basic-object>
        </template>
      </element>
      <element name="Element@1088305934" type="text/plain">
        <style>
          <basic-key name="border-top-width">1.0</basic-key>
          <basic-key name="border-top-style">none</basic-key>
          <basic-key name="border-top-color">black</basic-key>
          <basic-key name="border-left-width">1.0</basic-key>
          <basic-key name="border-left-style">none</basic-key>
          <basic-key name="border-left-color">black</basic-key>
          <basic-key name="border-bottom-width">1.0</basic-key>
          <basic-key name="border-bottom-style">none</basic-key>
          <basic-key name="border-bottom-color">black</basic-key>
          <basic-key name="border-right-width">1.0</basic-key>
          <basic-key name="border-right-style">none</basic-key>
          <basic-key name="border-right-color">black</basic-key>
          <basic-key name="border-break-width">0.0</basic-key>
          <basic-key name="border-break-style">none</basic-key>
          <basic-key name="border-break-color">black</basic-key>
          <basic-key name="border-top-right-radius-width">0.0</basic-key>
          <basic-key name="border-top-left-radius-width">0.0</basic-key>
          <basic-key name="border-bottom-right-radius-width">0.0</basic-key>
          <basic-key name="border-bottom-left-radius-width">0.0</basic-key>
          <basic-key name="border-top-right-radius-height">0.0</basic-key>
          <basic-key name="border-top-left-radius-height">0.0</basic-key>
          <basic-key name="border-bottom-right-radius-height">0.0</basic-key>
          <basic-key name="border-bottom-left-radius-height">0.0</basic-key>
          <basic-key name="padding-left">0.0</basic-key>
          <basic-key name="padding-top">0.0</basic-key>
          <basic-key name="padding-bottom">0.0</basic-key>
          <basic-key name="padding-right">0.0</basic-key>
          <basic-key name="x">0.0</basic-key>
          <basic-key name="y">25.0</basic-key>
          <basic-key name="min-width">482.0</basic-key>
          <basic-key name="min-height">25.0</basic-key>
          <basic-key name="paint">black</basic-key>
          <basic-key name="alignment">center</basic-key>
          <basic-key name="valignment">middle</basic-key>
          <basic-key name="dynamic_height">false</basic-key>
          <basic-key name="Excel.WrapText">true</basic-key>
          <basic-key name="font">Arial Unicode MS</basic-key>
          <basic-key name="font-size">14</basic-key>
          <basic-key name="line-height">0.0</basic-key>
          <basic-key name="font-bold">true</basic-key>
          <basic-key name="font-italic">false</basic-key>
          <basic-key name="font-underline">false</basic-key>
          <basic-key name="font-strikethrough">false</basic-key>
          <basic-key name="font-embedded">true</basic-key>
          <basic-key name="font-encoding">UTF-8</basic-key>
          <basic-key name="reserved-literal">..</basic-key>
          <basic-key name="trim-text-content">false</basic-key>
        </style>
        <template references="label">
          <basic-object name="content">СЛУЖБА ПО ТАРИФАМ ОРЛОВСКОЙ ОБЛАСТИ</basic-object>
        </template>
      </element>
      <element name="Element@1707707379" type="text/plain">
        <style>
          <basic-key name="border-top-width">1.0</basic-key>
          <basic-key name="border-top-style">none</basic-key>
          <basic-key name="border-top-color">black</basic-key>
          <basic-key name="border-left-width">1.0</basic-key>
          <basic-key name="border-left-style">none</basic-key>
          <basic-key name="border-left-color">black</basic-key>
          <basic-key name="border-bottom-width">1.0</basic-key>
          <basic-key name="border-bottom-style">none</basic-key>
          <basic-key name="border-bottom-color">black</basic-key>
          <basic-key name="border-right-width">1.0</basic-key>
          <basic-key name="border-right-style">none</basic-key>
          <basic-key name="border-right-color">black</basic-key>
          <basic-key name="border-break-width">0.0</basic-key>
          <basic-key name="border-break-style">none</basic-key>
          <basic-key name="border-break-color">black</basic-key>
          <basic-key name="border-top-right-radius-width">0.0</basic-key>
          <basic-key name="border-top-left-radius-width">0.0</basic-key>
          <basic-key name="border-bottom-right-radius-width">0.0</basic-key>
          <basic-key name="border-bottom-left-radius-width">0.0</basic-key>
          <basic-key name="border-top-right-radius-height">0.0</basic-key>
          <basic-key name="border-top-left-radius-height">0.0</basic-key>
          <basic-key name="border-bottom-right-radius-height">0.0</basic-key>
          <basic-key name="border-bottom-left-radius-height">0.0</basic-key>
          <basic-key name="padding-left">0.0</basic-key>
          <basic-key name="padding-top">0.0</basic-key>
          <basic-key name="padding-bottom">0.0</basic-key>
          <basic-key name="padding-right">0.0</basic-key>
          <basic-key name="x">0.0</basic-key>
          <basic-key name="y">55.0</basic-key>
          <basic-key name="min-width">482.0</basic-key>
          <basic-key name="min-height">25.0</basic-key>
          <basic-key name="paint">black</basic-key>
          <basic-key name="alignment">center</basic-key>
          <basic-key name="valignment">middle</basic-key>
          <basic-key name="dynamic_height">false</basic-key>
          <basic-key name="Excel.WrapText">false</basic-key>
          <basic-key name="font">Arial Unicode MS</basic-key>
          <basic-key name="font-size">14</basic-key>
          <basic-key name="line-height">0.0</basic-key>
          <basic-key name="font-bold">true</basic-key>
          <basic-key name="font-italic">false</basic-key>
          <basic-key name="font-underline">false</basic-key>
          <basic-key name="font-strikethrough">false</basic-key>
          <basic-key name="font-embedded">false</basic-key>
          <basic-key name="reserved-literal">..</basic-key>
          <basic-key name="trim-text-content">false</basic-key>
        </style>
        <template references="label">
          <basic-object name="content">П Р И К А З</basic-object>
        </template>
      </element>
    </report-header>
    <report-footer>
      <style>
        <basic-key name="pagebreak-before">false</basic-key>
        <basic-key name="pagebreak-after">false</basic-key>
        <basic-key name="border-top-width">1.0</basic-key>
        <basic-key name="border-top-style">none</basic-key>
        <basic-key name="border-top-color">black</basic-key>
        <basic-key name="border-left-width">1.0</basic-key>
        <basic-key name="border-left-style">none</basic-key>
        <basic-key name="border-left-color">black</basic-key>
        <basic-key name="border-bottom-width">1.0</basic-key>
        <basic-key name="border-bottom-style">none</basic-key>
        <basic-key name="border-bottom-color">black</basic-key>
        <basic-key name="border-right-width">1.0</basic-key>
        <basic-key name="border-right-style">none</basic-key>
        <basic-key name="border-right-color">black</basic-key>
        <basic-key name="border-break-width">0.0</basic-key>
        <basic-key name="border-break-style">none</basic-key>
        <basic-key name="border-break-color">black</basic-key>
        <basic-key name="border-top-right-radius-width">0.0</basic-key>
        <basic-key name="border-top-left-radius-width">0.0</basic-key>
        <basic-key name="border-bottom-right-radius-width">0.0</basic-key>
        <basic-key name="border-bottom-left-radius-width">0.0</basic-key>
        <basic-key name="border-top-right-radius-height">0.0</basic-key>
        <basic-key name="border-top-left-radius-height">0.0</basic-key>
        <basic-key name="border-bottom-right-radius-height">0.0</basic-key>
        <basic-key name="border-bottom-left-radius-height">0.0</basic-key>
        <basic-key name="padding-left">0.0</basic-key>
        <basic-key name="padding-top">0.0</basic-key>
        <basic-key name="padding-bottom">0.0</basic-key>
        <basic-key name="padding-right">0.0</basic-key>
      </style>
      <element name="Element@1823909363" type="text/plain">
        <style>
          <basic-key name="border-top-width">1.0</basic-key>
          <basic-key name="border-top-style">none</basic-key>
          <basic-key name="border-top-color">black</basic-key>
          <basic-key name="border-left-width">1.0</basic-key>
          <basic-key name="border-left-style">none</basic-key>
          <basic-key name="border-left-color">black</basic-key>
          <basic-key name="border-bottom-width">1.0</basic-key>
          <basic-key name="border-bottom-style">none</basic-key>
          <basic-key name="border-bottom-color">black</basic-key>
          <basic-key name="border-right-width">1.0</basic-key>
          <basic-key name="border-right-style">none</basic-key>
          <basic-key name="border-right-color">black</basic-key>
          <basic-key name="border-break-width">0.0</basic-key>
          <basic-key name="border-break-style">none</basic-key>
          <basic-key name="border-break-color">black</basic-key>
          <basic-key name="border-top-right-radius-width">0.0</basic-key>
          <basic-key name="border-top-left-radius-width">0.0</basic-key>
          <basic-key name="border-bottom-right-radius-width">0.0</basic-key>
          <basic-key name="border-bottom-left-radius-width">0.0</basic-key>
          <basic-key name="border-top-right-radius-height">0.0</basic-key>
          <basic-key name="border-top-left-radius-height">0.0</basic-key>
          <basic-key name="border-bottom-right-radius-height">0.0</basic-key>
          <basic-key name="border-bottom-left-radius-height">0.0</basic-key>
          <basic-key name="padding-left">0.0</basic-key>
          <basic-key name="padding-top">0.0</basic-key>
          <basic-key name="padding-bottom">0.0</basic-key>
          <basic-key name="padding-right">0.0</basic-key>
          <basic-key name="x">4.3423424</basic-key>
          <basic-key name="y">5.0</basic-key>
          <basic-key name="min-width">477.65765</basic-key>
          <basic-key name="min-height">55.0</basic-key>
          <basic-key name="paint">black</basic-key>
          <basic-key name="alignment">left</basic-key>
          <basic-key name="valignment">top</basic-key>
          <basic-key name="dynamic_height">false</basic-key>
          <basic-key name="Excel.WrapText">true</basic-key>
          <basic-key name="font">Arial Unicode MS</basic-key>
          <basic-key name="font-size">12</basic-key>
          <basic-key name="line-height">0.0</basic-key>
          <basic-key name="font-bold">false</basic-key>
          <basic-key name="font-italic">false</basic-key>
          <basic-key name="font-underline">false</basic-key>
          <basic-key name="font-strikethrough">false</basic-key>
          <basic-key name="font-embedded">true</basic-key>
          <basic-key name="font-encoding">UTF-8</basic-key>
          <basic-key name="reserved-literal">..</basic-key>
          <basic-key name="trim-text-content">false</basic-key>
        </style>
        <template references="message-field">
          <basic-object name="format">   3. Направить приказ лицензиату согласно установленному порядку.
   4  Контроль за исполнением настоящего приказа возложить на заместителя руководителя Службы $(ZAM_RUK_SERVICE).</basic-object>
          <basic-object name="nullValue"></basic-object>
        </template>
      </element>
      <element name="Element@645515091" type="text/plain">
        <style>
          <basic-key name="border-top-width">1.0</basic-key>
          <basic-key name="border-top-style">none</basic-key>
          <basic-key name="border-top-color">black</basic-key>
          <basic-key name="border-left-width">1.0</basic-key>
          <basic-key name="border-left-style">none</basic-key>
          <basic-key name="border-left-color">black</basic-key>
          <basic-key name="border-bottom-width">1.0</basic-key>
          <basic-key name="border-bottom-style">none</basic-key>
          <basic-key name="border-bottom-color">black</basic-key>
          <basic-key name="border-right-width">1.0</basic-key>
          <basic-key name="border-right-style">none</basic-key>
          <basic-key name="border-right-color">black</basic-key>
          <basic-key name="border-break-width">0.0</basic-key>
          <basic-key name="border-break-style">none</basic-key>
          <basic-key name="border-break-color">black</basic-key>
          <basic-key name="border-top-right-radius-width">0.0</basic-key>
          <basic-key name="border-top-left-radius-width">0.0</basic-key>
          <basic-key name="border-bottom-right-radius-width">0.0</basic-key>
          <basic-key name="border-bottom-left-radius-width">0.0</basic-key>
          <basic-key name="border-top-right-radius-height">0.0</basic-key>
          <basic-key name="border-top-left-radius-height">0.0</basic-key>
          <basic-key name="border-bottom-right-radius-height">0.0</basic-key>
          <basic-key name="border-bottom-left-radius-height">0.0</basic-key>
          <basic-key name="padding-left">0.0</basic-key>
          <basic-key name="padding-top">0.0</basic-key>
          <basic-key name="padding-bottom">0.0</basic-key>
          <basic-key name="padding-right">0.0</basic-key>
          <basic-key name="x">21.711712</basic-key>
          <basic-key name="y">120.0</basic-key>
          <basic-key name="min-width">112.9009</basic-key>
          <basic-key name="min-height">20.0</basic-key>
          <basic-key name="paint">black</basic-key>
          <basic-key name="alignment">left</basic-key>
          <basic-key name="valignment">middle</basic-key>
          <basic-key name="dynamic_height">false</basic-key>
          <basic-key name="Excel.WrapText">true</basic-key>
          <basic-key name="font">Arial Unicode MS</basic-key>
          <basic-key name="font-size">12</basic-key>
          <basic-key name="line-height">0.0</basic-key>
          <basic-key name="font-bold">false</basic-key>
          <basic-key name="font-italic">false</basic-key>
          <basic-key name="font-underline">false</basic-key>
          <basic-key name="font-strikethrough">false</basic-key>
          <basic-key name="font-embedded">true</basic-key>
          <basic-key name="font-encoding">UTF-8</basic-key>
          <basic-key name="reserved-literal">..</basic-key>
          <basic-key name="trim-text-content">false</basic-key>
        </style>
        <template references="label">
          <basic-object name="content">Руководитель Службы</basic-object>
        </template>
      </element>
      <element name="TextField@432884427" type="text/plain">
        <style>
          <basic-key name="border-top-width">1.0</basic-key>
          <basic-key name="border-top-style">none</basic-key>
          <basic-key name="border-top-color">black</basic-key>
          <basic-key name="border-left-width">1.0</basic-key>
          <basic-key name="border-left-style">none</basic-key>
          <basic-key name="border-left-color">black</basic-key>
          <basic-key name="border-bottom-width">1.0</basic-key>
          <basic-key name="border-bottom-style">none</basic-key>
          <basic-key name="border-bottom-color">black</basic-key>
          <basic-key name="border-right-width">1.0</basic-key>
          <basic-key name="border-right-style">none</basic-key>
          <basic-key name="border-right-color">black</basic-key>
          <basic-key name="border-break-width">0.0</basic-key>
          <basic-key name="border-break-style">none</basic-key>
          <basic-key name="border-break-color">black</basic-key>
          <basic-key name="border-top-right-radius-width">0.0</basic-key>
          <basic-key name="border-top-left-radius-width">0.0</basic-key>
          <basic-key name="border-bottom-right-radius-width">0.0</basic-key>
          <basic-key name="border-bottom-left-radius-width">0.0</basic-key>
          <basic-key name="border-top-right-radius-height">0.0</basic-key>
          <basic-key name="border-top-left-radius-height">0.0</basic-key>
          <basic-key name="border-bottom-right-radius-height">0.0</basic-key>
          <basic-key name="border-bottom-left-radius-height">0.0</basic-key>
          <basic-key name="padding-left">0.0</basic-key>
          <basic-key name="padding-top">0.0</basic-key>
          <basic-key name="padding-bottom">0.0</basic-key>
          <basic-key name="padding-right">0.0</basic-key>
          <basic-key name="x">369.0991</basic-key>
          <basic-key name="y">120.0</basic-key>
          <basic-key name="min-width">86.84685</basic-key>
          <basic-key name="min-height">20.0</basic-key>
          <basic-key name="paint">black</basic-key>
          <basic-key name="alignment">left</basic-key>
          <basic-key name="valignment">top</basic-key>
          <basic-key name="dynamic_height">false</basic-key>
          <basic-key name="Excel.WrapText">true</basic-key>
          <basic-key name="font">Arial Unicode MS</basic-key>
          <basic-key name="font-size">12</basic-key>
          <basic-key name="line-height">0.0</basic-key>
          <basic-key name="font-bold">false</basic-key>
          <basic-key name="font-italic">false</basic-key>
          <basic-key name="font-underline">false</basic-key>
          <basic-key name="font-strikethrough">false</basic-key>
          <basic-key name="font-embedded">true</basic-key>
          <basic-key name="font-encoding">UTF-8</basic-key>
          <basic-key name="reserved-literal">..</basic-key>
          <basic-key name="trim-text-content">false</basic-key>
        </style>
        <template references="string-field">
          <basic-object name="field">RUK_SERVICE</basic-object>
          <basic-object name="nullValue"></basic-object>
        </template>
      </element>
    </report-footer>
    <page-header>
      <style>
        <basic-key name="display-on-firstpage">true</basic-key>
        <basic-key name="display-on-lastpage">true</basic-key>
        <basic-key name="sticky">false</basic-key>
        <basic-key name="border-top-width">1.0</basic-key>
        <basic-key name="border-top-style">none</basic-key>
        <basic-key name="border-top-color">black</basic-key>
        <basic-key name="border-left-width">1.0</basic-key>
        <basic-key name="border-left-style">none</basic-key>
        <basic-key name="border-left-color">black</basic-key>
        <basic-key name="border-bottom-width">1.0</basic-key>
        <basic-key name="border-bottom-style">none</basic-key>
        <basic-key name="border-bottom-color">black</basic-key>
        <basic-key name="border-right-width">1.0</basic-key>
        <basic-key name="border-right-style">none</basic-key>
        <basic-key name="border-right-color">black</basic-key>
        <basic-key name="border-break-width">0.0</basic-key>
        <basic-key name="border-break-style">none</basic-key>
        <basic-key name="border-break-color">black</basic-key>
        <basic-key name="border-top-right-radius-width">0.0</basic-key>
        <basic-key name="border-top-left-radius-width">0.0</basic-key>
        <basic-key name="border-bottom-right-radius-width">0.0</basic-key>
        <basic-key name="border-bottom-left-radius-width">0.0</basic-key>
        <basic-key name="border-top-right-radius-height">0.0</basic-key>
        <basic-key name="border-top-left-radius-height">0.0</basic-key>
        <basic-key name="border-bottom-right-radius-height">0.0</basic-key>
        <basic-key name="border-bottom-left-radius-height">0.0</basic-key>
        <basic-key name="padding-left">0.0</basic-key>
        <basic-key name="padding-top">0.0</basic-key>
        <basic-key name="padding-bottom">0.0</basic-key>
        <basic-key name="padding-right">0.0</basic-key>
      </style>
    </page-header>
    <page-footer>
      <style>
        <basic-key name="display-on-firstpage">true</basic-key>
        <basic-key name="display-on-lastpage">true</basic-key>
        <basic-key name="border-top-width">1.0</basic-key>
        <basic-key name="border-top-style">none</basic-key>
        <basic-key name="border-top-color">black</basic-key>
        <basic-key name="border-left-width">1.0</basic-key>
        <basic-key name="border-left-style">none</basic-key>
        <basic-key name="border-left-color">black</basic-key>
        <basic-key name="border-bottom-width">1.0</basic-key>
        <basic-key name="border-bottom-style">none</basic-key>
        <basic-key name="border-bottom-color">black</basic-key>
        <basic-key name="border-right-width">1.0</basic-key>
        <basic-key name="border-right-style">none</basic-key>
        <basic-key name="border-right-color">black</basic-key>
        <basic-key name="border-break-width">0.0</basic-key>
        <basic-key name="border-break-style">none</basic-key>
        <basic-key name="border-break-color">black</basic-key>
        <basic-key name="border-top-right-radius-width">0.0</basic-key>
        <basic-key name="border-top-left-radius-width">0.0</basic-key>
        <basic-key name="border-bottom-right-radius-width">0.0</basic-key>
        <basic-key name="border-bottom-left-radius-width">0.0</basic-key>
        <basic-key name="border-top-right-radius-height">0.0</basic-key>
        <basic-key name="border-top-left-radius-height">0.0</basic-key>
        <basic-key name="border-bottom-right-radius-height">0.0</basic-key>
        <basic-key name="border-bottom-left-radius-height">0.0</basic-key>
        <basic-key name="padding-left">0.0</basic-key>
        <basic-key name="padding-top">0.0</basic-key>
        <basic-key name="padding-bottom">0.0</basic-key>
        <basic-key name="padding-right">0.0</basic-key>
      </style>
    </page-footer>
    <watermark>
      <style>
        <basic-key name="pagebreak-before">false</basic-key>
        <basic-key name="pagebreak-after">false</basic-key>
        <basic-key name="border-top-width">1.0</basic-key>
        <basic-key name="border-top-style">none</basic-key>
        <basic-key name="border-top-color">black</basic-key>
        <basic-key name="border-left-width">1.0</basic-key>
        <basic-key name="border-left-style">none</basic-key>
        <basic-key name="border-left-color">black</basic-key>
        <basic-key name="border-bottom-width">1.0</basic-key>
        <basic-key name="border-bottom-style">none</basic-key>
        <basic-key name="border-bottom-color">black</basic-key>
        <basic-key name="border-right-width">1.0</basic-key>
        <basic-key name="border-right-style">none</basic-key>
        <basic-key name="border-right-color">black</basic-key>
        <basic-key name="border-break-width">0.0</basic-key>
        <basic-key name="border-break-style">none</basic-key>
        <basic-key name="border-break-color">black</basic-key>
        <basic-key name="border-top-right-radius-width">0.0</basic-key>
        <basic-key name="border-top-left-radius-width">0.0</basic-key>
        <basic-key name="border-bottom-right-radius-width">0.0</basic-key>
        <basic-key name="border-bottom-left-radius-width">0.0</basic-key>
        <basic-key name="border-top-right-radius-height">0.0</basic-key>
        <basic-key name="border-top-left-radius-height">0.0</basic-key>
        <basic-key name="border-bottom-right-radius-height">0.0</basic-key>
        <basic-key name="border-bottom-left-radius-height">0.0</basic-key>
        <basic-key name="padding-left">0.0</basic-key>
        <basic-key name="padding-top">0.0</basic-key>
        <basic-key name="padding-bottom">0.0</basic-key>
        <basic-key name="padding-right">0.0</basic-key>
      </style>
    </watermark>
    <groups>
      <group name="default">
        <fields/>
        <group-header>
        </group-header>
        <group-footer>
        </group-footer>
      </group>
      <group name="group">
        <fields>
          <field>AGENT_NAME</field>
        </fields>
        <group-header>
          <style>
            <basic-key name="pagebreak-before">false</basic-key>
            <basic-key name="pagebreak-after">false</basic-key>
            <basic-key name="repeat-header">false</basic-key>
            <basic-key name="sticky">false</basic-key>
            <basic-key name="border-top-width">1.0</basic-key>
            <basic-key name="border-top-style">none</basic-key>
            <basic-key name="border-top-color">black</basic-key>
            <basic-key name="border-left-width">1.0</basic-key>
            <basic-key name="border-left-style">none</basic-key>
            <basic-key name="border-left-color">black</basic-key>
            <basic-key name="border-bottom-width">1.0</basic-key>
            <basic-key name="border-bottom-style">none</basic-key>
            <basic-key name="border-bottom-color">black</basic-key>
            <basic-key name="border-right-width">1.0</basic-key>
            <basic-key name="border-right-style">none</basic-key>
            <basic-key name="border-right-color">black</basic-key>
            <basic-key name="border-break-width">0.0</basic-key>
            <basic-key name="border-break-style">none</basic-key>
            <basic-key name="border-break-color">black</basic-key>
            <basic-key name="border-top-right-radius-width">0.0</basic-key>
            <basic-key name="border-top-left-radius-width">0.0</basic-key>
            <basic-key name="border-bottom-right-radius-width">0.0</basic-key>
            <basic-key name="border-bottom-left-radius-width">0.0</basic-key>
            <basic-key name="border-top-right-radius-height">0.0</basic-key>
            <basic-key name="border-top-left-radius-height">0.0</basic-key>
            <basic-key name="border-bottom-right-radius-height">0.0</basic-key>
            <basic-key name="border-bottom-left-radius-height">0.0</basic-key>
            <basic-key name="padding-left">0.0</basic-key>
            <basic-key name="padding-top">0.0</basic-key>
            <basic-key name="padding-bottom">0.0</basic-key>
            <basic-key name="padding-right">0.0</basic-key>
          </style>
          <element name="Element@540523637" type="text/plain">
            <style>
              <basic-key name="border-top-width">1.0</basic-key>
              <basic-key name="border-top-style">none</basic-key>
              <basic-key name="border-top-color">black</basic-key>
              <basic-key name="border-left-width">1.0</basic-key>
              <basic-key name="border-left-style">none</basic-key>
              <basic-key name="border-left-color">black</basic-key>
              <basic-key name="border-bottom-width">1.0</basic-key>
              <basic-key name="border-bottom-style">none</basic-key>
              <basic-key name="border-bottom-color">black</basic-key>
              <basic-key name="border-right-width">1.0</basic-key>
              <basic-key name="border-right-style">none</basic-key>
              <basic-key name="border-right-color">black</basic-key>
              <basic-key name="border-break-width">0.0</basic-key>
              <basic-key name="border-break-style">none</basic-key>
              <basic-key name="border-break-color">black</basic-key>
              <basic-key name="border-top-right-radius-width">0.0</basic-key>
              <basic-key name="border-top-left-radius-width">0.0</basic-key>
              <basic-key name="border-bottom-right-radius-width">0.0</basic-key>
              <basic-key name="border-bottom-left-radius-width">0.0</basic-key>
              <basic-key name="border-top-right-radius-height">0.0</basic-key>
              <basic-key name="border-top-left-radius-height">0.0</basic-key>
              <basic-key name="border-bottom-right-radius-height">0.0</basic-key>
              <basic-key name="border-bottom-left-radius-height">0.0</basic-key>
              <basic-key name="padding-left">0.0</basic-key>
              <basic-key name="padding-top">0.0</basic-key>
              <basic-key name="padding-bottom">0.0</basic-key>
              <basic-key name="padding-right">0.0</basic-key>
              <basic-key name="x">4.3423424</basic-key>
              <basic-key name="y">0.0</basic-key>
              <basic-key name="min-width">477.65765</basic-key>
              <basic-key name="min-height">120.0</basic-key>
              <basic-key name="paint">black</basic-key>
              <basic-key name="alignment">left</basic-key>
              <basic-key name="valignment">top</basic-key>
              <basic-key name="dynamic_height">true</basic-key>
              <basic-key name="Excel.WrapText">true</basic-key>
              <basic-key name="font">Arial Unicode MS</basic-key>
              <basic-key name="font-size">12</basic-key>
              <basic-key name="line-height">0.0</basic-key>
              <basic-key name="font-bold">false</basic-key>
              <basic-key name="font-italic">false</basic-key>
              <basic-key name="font-underline">false</basic-key>
              <basic-key name="font-strikethrough">false</basic-key>
              <basic-key name="font-embedded">true</basic-key>
              <basic-key name="font-encoding">UTF-8</basic-key>
              <basic-key name="reserved-literal">..</basic-key>
              <basic-key name="trim-text-content">false</basic-key>
            </style>
            <template references="message-field">
              <basic-object name="format">   1. Отказать в возобновлении действия лицензии серии $(LICENSE_SERIE) № $(LICENSE_NUMBER)  сроком действия $(LICENSE_DATE, date, dd.MM.yyyy)г. по $(LICENSE_END_DATE, date, dd.MM.yyyy)г., выданной $(AGENT_NAME) ($(AGENT_ADDRESS)) на розничную продажу алкогольной продукции в отношении $(LIC_OBJECT_TIP) «$(LIC_OBJECT_NAME)» по адресу $(LIC_OBJECT_KLADR).
   2. Основание отказа в возобновлении действия лицензии:
   Неустранение нарушений лицензионных требований и условий, установленных Федеральным законом №171-ФЗ, Законом Орловской области №564-ОЗ, послуживших основание для приостановления действия лицензии, а именно:  
   </basic-object>
              <basic-object name="nullValue"></basic-object>
            </template>
          </element>
          <element name="Element@1823909363" type="text/plain">
            <style>
              <basic-key name="border-top-width">1.0</basic-key>
              <basic-key name="border-top-style">none</basic-key>
              <basic-key name="border-top-color">black</basic-key>
              <basic-key name="border-left-width">1.0</basic-key>
              <basic-key name="border-left-style">none</basic-key>
              <basic-key name="border-left-color">black</basic-key>
              <basic-key name="border-bottom-width">1.0</basic-key>
              <basic-key name="border-bottom-style">none</basic-key>
              <basic-key name="border-bottom-color">black</basic-key>
              <basic-key name="border-right-width">1.0</basic-key>
              <basic-key name="border-right-style">none</basic-key>
              <basic-key name="border-right-color">black</basic-key>
              <basic-key name="border-break-width">0.0</basic-key>
              <basic-key name="border-break-style">none</basic-key>
              <basic-key name="border-break-color">black</basic-key>
              <basic-key name="border-top-right-radius-width">0.0</basic-key>
              <basic-key name="border-top-left-radius-width">0.0</basic-key>
              <basic-key name="border-bottom-right-radius-width">0.0</basic-key>
              <basic-key name="border-bottom-left-radius-width">0.0</basic-key>
              <basic-key name="border-top-right-radius-height">0.0</basic-key>
              <basic-key name="border-top-left-radius-height">0.0</basic-key>
              <basic-key name="border-bottom-right-radius-height">0.0</basic-key>
              <basic-key name="border-bottom-left-radius-height">0.0</basic-key>
              <basic-key name="padding-left">0.0</basic-key>
              <basic-key name="padding-top">0.0</basic-key>
              <basic-key name="padding-bottom">0.0</basic-key>
              <basic-key name="padding-right">0.0</basic-key>
              <basic-key name="x">4.3423424</basic-key>
              <basic-key name="y">125.0</basic-key>
              <basic-key name="min-width">477.65765</basic-key>
              <basic-key name="min-height">85.0</basic-key>
              <basic-key name="paint">black</basic-key>
              <basic-key name="alignment">left</basic-key>
              <basic-key name="valignment">top</basic-key>
              <basic-key name="dynamic_height">true</basic-key>
              <basic-key name="Excel.WrapText">true</basic-key>
              <basic-key name="font">Arial Unicode MS</basic-key>
              <basic-key name="font-size">10</basic-key>
              <basic-key name="line-height">0.0</basic-key>
              <basic-key name="font-bold">false</basic-key>
              <basic-key name="font-italic">false</basic-key>
              <basic-key name="font-underline">false</basic-key>
              <basic-key name="font-strikethrough">false</basic-key>
              <basic-key name="font-embedded">true</basic-key>
              <basic-key name="font-encoding">UTF-8</basic-key>
              <basic-key name="reserved-literal">..</basic-key>
              <basic-key name="trim-text-content">false</basic-key>
            </style>
            <template references="message-field">
              <basic-object name="format">   Неустранение нарушений лицензионных требований и условий, установленных Федеральным законом от 22.11.1995г. №171-ФЗ (в ред.Федерального закона от 21.07.05г. №102-ФЗ) «О государственном регулировании производства и оборота этилового спирта, алкогольной и спиртосодержащей продукции», Законом Орловской области от 26.12.2005г. №564-ОЗ «О государственном регулировании производства и оборота этилового спирта алкогольной и спиртосодержащей продукции на территории Орловской области», послуживших основанием для приостановления действия лицензии, а именно: </basic-object>
              <basic-object name="nullValue"></basic-object>
            </template>
          </element>
        </group-header>
        <group-footer>
          <style>
            <basic-key name="pagebreak-before">false</basic-key>
            <basic-key name="pagebreak-after">false</basic-key>
            <basic-key name="repeat-header">false</basic-key>
            <basic-key name="sticky">false</basic-key>
            <basic-key name="border-top-width">1.0</basic-key>
            <basic-key name="border-top-style">none</basic-key>
            <basic-key name="border-top-color">black</basic-key>
            <basic-key name="border-left-width">1.0</basic-key>
            <basic-key name="border-left-style">none</basic-key>
            <basic-key name="border-left-color">black</basic-key>
            <basic-key name="border-bottom-width">1.0</basic-key>
            <basic-key name="border-bottom-style">none</basic-key>
            <basic-key name="border-bottom-color">black</basic-key>
            <basic-key name="border-right-width">1.0</basic-key>
            <basic-key name="border-right-style">none</basic-key>
            <basic-key name="border-right-color">black</basic-key>
            <basic-key name="border-break-width">0.0</basic-key>
            <basic-key name="border-break-style">none</basic-key>
            <basic-key name="border-break-color">black</basic-key>
            <basic-key name="border-top-right-radius-width">0.0</basic-key>
            <basic-key name="border-top-left-radius-width">0.0</basic-key>
            <basic-key name="border-bottom-right-radius-width">0.0</basic-key>
            <basic-key name="border-bottom-left-radius-width">0.0</basic-key>
            <basic-key name="border-top-right-radius-height">0.0</basic-key>
            <basic-key name="border-top-left-radius-height">0.0</basic-key>
            <basic-key name="border-bottom-right-radius-height">0.0</basic-key>
            <basic-key name="border-bottom-left-radius-height">0.0</basic-key>
            <basic-key name="padding-left">0.0</basic-key>
            <basic-key name="padding-top">0.0</basic-key>
            <basic-key name="padding-bottom">0.0</basic-key>
            <basic-key name="padding-right">0.0</basic-key>
          </style>
          <element name="Element@1523332131" type="text/plain">
            <style>
              <basic-key name="border-top-width">1.0</basic-key>
              <basic-key name="border-top-style">none</basic-key>
              <basic-key name="border-top-color">black</basic-key>
              <basic-key name="border-left-width">1.0</basic-key>
              <basic-key name="border-left-style">none</basic-key>
              <basic-key name="border-left-color">black</basic-key>
              <basic-key name="border-bottom-width">1.0</basic-key>
              <basic-key name="border-bottom-style">none</basic-key>
              <basic-key name="border-bottom-color">black</basic-key>
              <basic-key name="border-right-width">1.0</basic-key>
              <basic-key name="border-right-style">none</basic-key>
              <basic-key name="border-right-color">black</basic-key>
              <basic-key name="border-break-width">0.0</basic-key>
              <basic-key name="border-break-style">none</basic-key>
              <basic-key name="border-break-color">black</basic-key>
              <basic-key name="border-top-right-radius-width">0.0</basic-key>
              <basic-key name="border-top-left-radius-width">0.0</basic-key>
              <basic-key name="border-bottom-right-radius-width">0.0</basic-key>
              <basic-key name="border-bottom-left-radius-width">0.0</basic-key>
              <basic-key name="border-top-right-radius-height">0.0</basic-key>
              <basic-key name="border-top-left-radius-height">0.0</basic-key>
              <basic-key name="border-bottom-right-radius-height">0.0</basic-key>
              <basic-key name="border-bottom-left-radius-height">0.0</basic-key>
              <basic-key name="padding-left">0.0</basic-key>
              <basic-key name="padding-top">0.0</basic-key>
              <basic-key name="padding-bottom">0.0</basic-key>
              <basic-key name="padding-right">0.0</basic-key>
              <basic-key name="x">4.3423424</basic-key>
              <basic-key name="y">0.0</basic-key>
              <basic-key name="min-width">477.65765</basic-key>
              <basic-key name="min-height">15.0</basic-key>
              <basic-key name="paint">black</basic-key>
              <basic-key name="alignment">left</basic-key>
              <basic-key name="valignment">top</basic-key>
              <basic-key name="dynamic_height">true</basic-key>
              <basic-key name="Excel.WrapText">false</basic-key>
              <basic-key name="font">Arial Unicode MS</basic-key>
              <basic-key name="font-size">12</basic-key>
              <basic-key name="line-height">0.0</basic-key>
              <basic-key name="font-bold">false</basic-key>
              <basic-key name="font-italic">false</basic-key>
              <basic-key name="font-underline">false</basic-key>
              <basic-key name="font-strikethrough">false</basic-key>
              <basic-key name="font-embedded">true</basic-key>
              <basic-key name="font-encoding">UTF-8</basic-key>
              <basic-key name="reserved-literal">..</basic-key>
              <basic-key name="trim-text-content">false</basic-key>
            </style>
            <template references="message-field">
              <basic-object name="format">$(PRIKAZ_TEXT)</basic-object>
              <basic-object name="nullValue"></basic-object>
            </template>
          </element>
        </group-footer>
      </group>
    </groups>
    <itemband>
      <style>
        <basic-key name="pagebreak-before">false</basic-key>
        <basic-key name="pagebreak-after">false</basic-key>
        <basic-key name="border-top-width">1.0</basic-key>
        <basic-key name="border-top-style">none</basic-key>
        <basic-key name="border-top-color">black</basic-key>
        <basic-key name="border-left-width">1.0</basic-key>
        <basic-key name="border-left-style">none</basic-key>
        <basic-key name="border-left-color">black</basic-key>
        <basic-key name="border-bottom-width">1.0</basic-key>
        <basic-key name="border-bottom-style">none</basic-key>
        <basic-key name="border-bottom-color">black</basic-key>
        <basic-key name="border-right-width">1.0</basic-key>
        <basic-key name="border-right-style">none</basic-key>
        <basic-key name="border-right-color">black</basic-key>
        <basic-key name="border-break-width">0.0</basic-key>
        <basic-key name="border-break-style">none</basic-key>
        <basic-key name="border-break-color">black</basic-key>
        <basic-key name="border-top-right-radius-width">0.0</basic-key>
        <basic-key name="border-top-left-radius-width">0.0</basic-key>
        <basic-key name="border-bottom-right-radius-width">0.0</basic-key>
        <basic-key name="border-bottom-left-radius-width">0.0</basic-key>
        <basic-key name="border-top-right-radius-height">0.0</basic-key>
        <basic-key name="border-top-left-radius-height">0.0</basic-key>
        <basic-key name="border-bottom-right-radius-height">0.0</basic-key>
        <basic-key name="border-bottom-left-radius-height">0.0</basic-key>
        <basic-key name="padding-left">0.0</basic-key>
        <basic-key name="padding-top">0.0</basic-key>
        <basic-key name="padding-bottom">0.0</basic-key>
        <basic-key name="padding-right">0.0</basic-key>
      </style>
    </itemband>
    <no-data-band>
      <style>
        <basic-key name="pagebreak-before">false</basic-key>
        <basic-key name="pagebreak-after">false</basic-key>
        <basic-key name="border-top-width">1.0</basic-key>
        <basic-key name="border-top-style">none</basic-key>
        <basic-key name="border-top-color">black</basic-key>
        <basic-key name="border-left-width">1.0</basic-key>
        <basic-key name="border-left-style">none</basic-key>
        <basic-key name="border-left-color">black</basic-key>
        <basic-key name="border-bottom-width">1.0</basic-key>
        <basic-key name="border-bottom-style">none</basic-key>
        <basic-key name="border-bottom-color">black</basic-key>
        <basic-key name="border-right-width">1.0</basic-key>
        <basic-key name="border-right-style">none</basic-key>
        <basic-key name="border-right-color">black</basic-key>
        <basic-key name="border-break-width">0.0</basic-key>
        <basic-key name="border-break-style">none</basic-key>
        <basic-key name="border-break-color">black</basic-key>
        <basic-key name="border-top-right-radius-width">0.0</basic-key>
        <basic-key name="border-top-left-radius-width">0.0</basic-key>
        <basic-key name="border-bottom-right-radius-width">0.0</basic-key>
        <basic-key name="border-bottom-left-radius-width">0.0</basic-key>
        <basic-key name="border-top-right-radius-height">0.0</basic-key>
        <basic-key name="border-top-left-radius-height">0.0</basic-key>
        <basic-key name="border-bottom-right-radius-height">0.0</basic-key>
        <basic-key name="border-bottom-left-radius-height">0.0</basic-key>
        <basic-key name="padding-left">0.0</basic-key>
        <basic-key name="padding-top">0.0</basic-key>
        <basic-key name="padding-bottom">0.0</basic-key>
        <basic-key name="padding-right">0.0</basic-key>
      </style>
    </no-data-band>
  </report-description>
  <functions>
    <property-ref name="report.name" class="java.lang.String">Report</property-ref>
  </functions>
</report-definition>
